predacons/__init__.py
predacons/src/__init__.py
predacons/src/data_preparation.py
predacons/src/embeddings.py
predacons/src/generate.py
predacons/src/kv_cache_model.py
predacons/src/load_data.py
predacons/src/predacons.py
predacons/src/speculative_decode.py
predacons/src/speculative_fast_generation.py
predacons/src/train_predacons.py
predacons-0.0.130.dist-info/licenses/LICENSE-AGPL
predacons-0.0.130.dist-info/licenses/LICENSE-COMMERCIAL-PERPETUAL
predacons-0.0.130.dist-info/licenses/LICENSE-COMMERCIAL-YEARLY
predacons-0.0.130.dist-info/METADATA
predacons-0.0.130.dist-info/WHEEL
predacons-0.0.130.dist-info/top_level.txt
predacons-0.0.130.dist-info/RECORD
