Metadata-Version: 2.4
Name: predacons
Version: 0.0.130
Summary: A python library based on transformers for transfer learning
Home-page: https://github.com/shouryashashank/predacons
Author: shouryashashank
Author-email: shouryashashank@gmail.com
License: AGPLv3+
Classifier: License :: OSI Approved :: GNU Affero General Public License v3 or later (AGPLv3+)
Classifier: Programming Language :: Python :: 3.10
Classifier: Operating System :: OS Independent
Requires-Python: >=3.10
License-File: LICENSE-AGPL
License-File: LICENSE-COMMERCIAL-PERPETUAL
License-File: LICENSE-COMMERCIAL-YEARLY
Requires-Dist: bson>=0.5.10
Requires-Dist: pandas>=1.5.3
Requires-Dist: numpy>=1.24.1
Requires-Dist: regex>=2021.4.4
Requires-Dist: pypdf>=5.3.0
Requires-Dist: docx>=0.2.4
Requires-Dist: python-docx>=1.0.1
Requires-Dist: transformers>=4.52.3
Requires-Dist: einops>=0.7.0
Requires-Dist: openai>=1.12.0
Requires-Dist: typing-extensions>=4.9.0
Requires-Dist: peft>=0.8.2
Requires-Dist: trl>=0.8.1
Provides-Extra: dev
Requires-Dist: pytest>=7.0; extra == "dev"
Requires-Dist: twine>=4.0.2; extra == "dev"
Dynamic: author
Dynamic: author-email
Dynamic: classifier
Dynamic: description
Dynamic: description-content-type
Dynamic: home-page
Dynamic: license
Dynamic: license-file
Dynamic: provides-extra
Dynamic: requires-dist
Dynamic: requires-python
Dynamic: summary
